lm_simulator_api/__init__.py
lm_simulator_api/config.py
lm_simulator_api/constants.py
lm_simulator_api/crud.py
lm_simulator_api/database.py
lm_simulator_api/main.py
lm_simulator_api/models.py
lm_simulator_api/schemas.py
lm_simulator_api/version.py
license_manager_simulator_api-4.5.0.dist-info/METADATA
license_manager_simulator_api-4.5.0.dist-info/WHEEL
license_manager_simulator_api-4.5.0.dist-info/licenses/LICENSE
license_manager_simulator_api-4.5.0.dist-info/RECORD
