Metadata-Version: 2.4
Name: license-manager-simulator-api
Version: 4.5.0
Summary: Provides an API for interfacing with License Manager Simulator
License: MIT
License-File: LICENSE
Author: OmniVector Solutions
Author-email: info@omnivector.solutions
Requires-Python: >=3.12,<4.0
Classifier: License :: OSI Approved :: MIT License
Classifier: Programming Language :: Python :: 3
Classifier: Programming Language :: Python :: 3.12
Classifier: Programming Language :: Python :: 3.13
Classifier: Programming Language :: Python :: 3.14
Requires-Dist: SQLAlchemy[mypy] (>=2.0.43,<3.0.0)
Requires-Dist: asyncpg (>=0.30.0,<0.31.0)
Requires-Dist: fastapi[all] (>=0.116.2,<0.117.0)
Requires-Dist: httpx (>=0.28.1,<0.29.0)
Requires-Dist: psycopg2 (==2.9.10)
Requires-Dist: py-buzz (==7.2.0)
Requires-Dist: pydantic (>=2.11.9,<3.0.0)
Requires-Dist: pydantic-settings (>=2.10.1,<3.0.0)
Requires-Dist: requests (>=2.32.5,<3.0.0)
Requires-Dist: toml (>=0.10.2,<0.11.0)
Requires-Dist: uvicorn (>=0.35.0,<0.36.0)
Requires-Dist: yarl (>=1.20.1,<2.0.0)
Project-URL: Documentation, https://omnivector-solutions.github.io/license-manager/
Project-URL: Repository, https://github.com/omnivector-solutions/license-manager
